COPYING.txt
LICENSE
MANIFEST.in
README.rst
setup.py
pg_python/__init__.py
pg_python/_db_object.py
pg_python/_delete.py
pg_python/_read.py
pg_python/_update.py
pg_python/_write.py
pg_python/pg_chrome_response.py
pg_python/pg_chunks.py
pg_python/pg_company.py
pg_python/pg_crawler.py
pg_python/pg_excel.py
pg_python/pg_local.py
pg_python/pg_net.py
pg_python/pg_python.py
pg_python/pg_response.py
pg_python/pg_table.py
pg_python/pg_test.py
pg_python/pg_time.py
pg_python.egg-info/PKG-INFO
pg_python.egg-info/SOURCES.txt
pg_python.egg-info/dependency_links.txt
pg_python.egg-info/not-zip-safe
pg_python.egg-info/requires.txt
pg_python.egg-info/top_level.txt